Metadata-Version: 2.1
Name: postikodi
Version: 0.0.1
Summary: Tanzania TCRA postikodi library
Author: ImaniMrosso
